sqlalchemy_get_or_create/__init__.py
sqlalchemy_get_or_create-0.1.5.dist-info/LICENSE
sqlalchemy_get_or_create-0.1.5.dist-info/WHEEL
sqlalchemy_get_or_create-0.1.5.dist-info/METADATA
sqlalchemy_get_or_create-0.1.5.dist-info/RECORD
