Metadata-Version: 2.1
Name: sqlalchemy-get-or-create
Version: 0.1.5
Summary: SQLAlchemy versions of Django's get_or_create() and update_or_create()
Home-page: https://github.com/enricobarzetti/sqlalchemy_get_or_create
Author: Enrico Barzetti
Author-email: enricobarzetti@gmail.com
Requires-Python: >=3.7,<4.0
Classifier: Programming Language :: Python :: 3
Classifier: Programming Language :: Python :: 3.7
Classifier: Programming Language :: Python :: 3.8
Requires-Dist: sqlalchemy (>=1.3.0,<2.0.0)
